setup.py
weatherpy2/__init__.py
weatherpy2/setup.py
weatherpy2/weatherpy2.py
weatherpy2.egg-info/PKG-INFO
weatherpy2.egg-info/SOURCES.txt
weatherpy2.egg-info/dependency_links.txt
weatherpy2.egg-info/requires.txt
weatherpy2.egg-info/top_level.txt