Metadata-Version: 2.1
Name: weatherpy2
Version: 1.2.1
Summary: Easy weather forcasting for Python 3
Home-page: https://github.com/GamerXZEN/weatherpy2
Author: GamerXZEN
Author-email: codspecialops@gmail.com
Keywords: weather,forecast,python
Classifier: Development Status :: 4 - Beta
Classifier: Intended Audience :: Developers
Classifier: Topic :: Software Development :: Build Tools
Classifier: License :: OSI Approved :: MIT License
Classifier: Programming Language :: Python :: 3.7
Classifier: Programming Language :: Python :: 3.8
Classifier: Programming Language :: Python :: 3.9
Classifier: Programming Language :: Python :: 3.10
Classifier: Programming Language :: Python :: 3.11
Classifier: Programming Language :: Python :: 3.12
